{
  "_TConcrete": {
    "en": "Concrete",
    "cs": "Beton",
    "de": "Beton",
    "es-419": "Concreto",
    "es-ES": "Hormigón",
    "fi": "Betoni",
    "fr": "Béton",
    "hu": "Beton",
    "it": "Calcestruzzo",
    "ja": "コンクリート",
    "ko": "콘크리트",
    "lt": "Betonas",
    "nl": "Beton",
    "pl": "Beton",
    "pt-BR": "Concreto",
    "ru": "Бетон",
    "sv": "Betong",
    "tr": "Beton",
    "uk": "Бетон",
    "vi": "Bê tông",
    "zh-Hans": "混凝土",
    "zh-Hant": "混凝土"
  },
  "_TContainer": {
    "en": "Container",
    "cs": "Kontejner",
    "es-419": "Contenedor",
    "es-ES": "Contenedor",
    "fi": "Kontti",
    "fr": "Conteneur",
    "hu": "Konténer",
    "ja": "コンテナ",
    "ko": "컨테이너",
    "lt": "Konteineris",
    "pl": "Kontener",
    "pt-BR": "Recipiente",
    "ru": "Контейнер",
    "tr": "Konteyner",
    "uk": "Контейнер",
    "zh-Hans": "集装箱",
    "zh-Hant": "貨櫃"
  },
  "_TFinalProduct": {
    "en": "Final Product",
    "cs": "Finální produkt",
    "de": "Endprodukt",
    "es-419": "Producto final",
    "es-ES": "Producto final",
    "fi": "Lopputuote",
    "fr": "PRODUIT FINAL",
    "hu": "Végtermék",
    "it": "Prodotto finale",
    "ja": "完成した製品",
    "ko": "최종 제품",
    "lt": "Galutinis produktas",
    "nl": "Eindproduct",
    "pl": "Produkt finalny",
    "pt-BR": "Produto Final",
    "ru": "Готовый Продукт",
    "sv": "Slutprodukt",
    "tr": "Son Ürün",
    "uk": "Кінцевий продукт",
    "vi": "Thành phẩm",
    "zh-Hans": "成品",
    "zh-Hant": "成品"
  },
  "_TFood": {
    "en": "Food",
    "cs": "Jídlo",
    "de": "Essen",
    "es-419": "Comida",
    "es-ES": "Comida",
    "fi": "Ruoka",
    "fr": "ALIMENTS",
    "hu": "Étel",
    "it": "Cibo",
    "ja": "食品",
    "ko": "음식",
    "lt": "Maistas",
    "nl": "Eten",
    "pl": "Żywność",
    "pt-BR": "Comida",
    "ru": "Еда",
    "sv": "Mat",
    "tr": "Yiyecek",
    "uk": "Продукти",
    "zh-Hans": "餐饮",
    "zh-Hant": "食物"
  },
  "_TFurniture": {
    "en": "Furniture",
    "cs": "Nábytek",
    "de": "Möbel",
    "es-419": "Muebles",
    "es-ES": "Muebles",
    "fi": "Huonekalu",
    "fr": "Meubles",
    "hu": "Bútor",
    "it": "Arredamento",
    "ja": "家具",
    "ko": "가구",
    "lt": "Baldai",
    "nl": "Meubilair",
    "pl": "Meble",
    "pt-BR": "Mobília",
    "ru": "Мебель",
    "sv": "Möbler",
    "tr": "Mobilya",
    "uk": "Меблі",
    "vi": "Đồ nội thất",
    "zh-Hans": "家具类",
    "zh-Hant": "家具"
  },
  "_TLargePackage": {
    "en": "Pallet",
    "cs": "Paleta",
    "de": "Palette",
    "es-419": "Palé",
    "es-ES": "Palet",
    "fi": "Kuormalava",
    "fr": "Palette",
    "hu": "Raklap",
    "ja": "パレット",
    "ko": "파렛트",
    "lt": "Paletė",
    "pl": "Paleta",
    "pt-BR": "Palete",
    "ru": "Поддон",
    "sv": "Lastpall",
    "tr": "Palet",
    "uk": "Палета",
    "vi": "Kiện hàng",
    "zh-Hans": "货盘",
    "zh-Hant": "棧板"
  },
  "_TLog": {
    "en": "Log",
    "cs": "Klády",
    "de": "Baumstamm",
    "es-419": "Troncos",
    "es-ES": "Troncos",
    "fi": "Tukki",
    "fr": "Journal",
    "hu": "Rönk",
    "it": "Ceppo",
    "ja": "丸太",
    "ko": "통나무",
    "lt": "Rąstas",
    "nl": "Boomstam",
    "pl": "Kłoda",
    "pt-BR": "Tora",
    "ru": "Бревно",
    "sv": "Stock",
    "tr": "Kütük",
    "uk": "Ліс",
    "vi": "Khúc gỗ",
    "zh-Hans": "原木",
    "zh-Hant": "原木"
  },
  "_TMilitarySupply": {
    "en": "Military Supply",
    "cs": "Vojenské zásoby",
    "de": "Militärische Versorgung",
    "es-419": "Suministro militar",
    "es-ES": "Suministro Militar",
    "fi": "Sotatarvikkeet",
    "fr": "Ravitaillement militaire",
    "hu": "Katonai Ellátmány",
    "it": "Fornitura militare",
    "ja": "軍需品",
    "ko": "군수품",
    "lt": "Karinės prekės",
    "nl": "Militaire bevoorrading",
    "pl": "Zaopatrzenie wojskowe",
    "pt-BR": "Suprimento Militar",
    "ru": "Военное снабжение",
    "sv": "Militärförråd",
    "tr": "Askeri Erzak",
    "uk": "Військові припаси",
    "zh-Hans": "军用补给",
    "zh-Hant": "軍用物資"
  },
  "_TSand": {
    "en": "Sand",
    "cs": "Písek",
    "es-419": "Arena",
    "es-ES": "Arena",
    "fi": "Hiekka",
    "fr": "Sable",
    "hu": "Homok",
    "it": "Sabbia",
    "ja": "砂",
    "ko": "모래",
    "lt": "Smėlis",
    "nl": "Zand",
    "pl": "Piasek",
    "pt-BR": "Areia",
    "ru": "Песок",
    "tr": "Kum",
    "uk": "Пісок",
    "vi": "Cát",
    "zh-Hans": "沙",
    "zh-Hant": "沙"
  },
  "_TSmallPackage2": {
    "en": "Box",
    "es-419": "Caja",
    "es-ES": "Caja",
    "fr": "Carton",
    "hu": "Doboz",
    "it": "Scatola",
    "ja": "箱",
    "lt": "Dėžė",
    "nl": "Doos",
    "pl": "Skrzynka",
    "pt-BR": "Caixa",
    "ru": "Коробка",
    "tr": "Kutu",
    "uk": "Коробка",
    "zh-Hans": "纸箱盒子",
    "zh-Hant": "箱子"
  },
  "_TWood": {
    "en": "Wood",
    "cs": "Dřevo",
    "de": "Holz",
    "es-419": "Madera",
    "es-ES": "Madera",
    "fi": "Puu",
    "fr": "Bois",
    "hu": "Fa",
    "it": "Legno",
    "ja": "木材",
    "ko": "목재",
    "lt": "Mediena",
    "nl": "Hout",
    "pl": "Drewno",
    "pt-BR": "Madeira",
    "ru": "Дерево",
    "sv": "Trä",
    "tr": "Odun",
    "uk": "Деревина",
    "vi": "Gỗ",
    "zh-Hans": "木",
    "zh-Hant": "木材"
  }
}
